fissure_engine/__init__.py
fissure_engine/common.py
fissure_engine/fissure_engine.py
fissure_engine-1.0.12.dist-info/METADATA
fissure_engine-1.0.12.dist-info/WHEEL
fissure_engine-1.0.12.dist-info/top_level.txt
fissure_engine-1.0.12.dist-info/RECORD
