Metadata-Version: 2.4
Name: fissure-engine
Version: 1.0.12
Summary: Engine for getting fissure information in Warframe.
Author: Jacob McBride
Author-email: jake55111@gmail.com
Keywords: warframe,fissures
Classifier: Programming Language :: Python :: 3
Classifier: Operating System :: OS Independent
Requires-Dist: aiohttp==3.10.11
Requires-Dist: ordered-set~=4.1.0
Requires-Dist: tenacity~=8.2.3
Dynamic: author
Dynamic: author-email
Dynamic: classifier
Dynamic: description
Dynamic: keywords
Dynamic: requires-dist
Dynamic: summary
